triggers/rs/hdl/rs.sv
module rs(input r, input s, output logic q, output logic nq);


assign q   = ~(nq | r);
assign nq  = ~( q | s);


endmodule

triggers/rs/hdl/testbench.sv
module testbench;
logic[3:0] i;
logic o, no;


initial begin
  $dumpfile("test.vcd");
  $dumpvars;

  for (i = 4'b0; i<4'b1111; i++) begin
    #5;
  end
  //i = '0;
  $finish;
end


rs dut(.r(i[3]), .s(i[2]), .q(o), .nq(no));

endmodule

triggers/rs/hdl/test.vcd
$date
	Tue Jan 28 01:54:37 2025
$end
$version
	Icarus Verilog
$end
$timescale
	1s
$end
$scope module testbench $end
$var wire 1 ! o $end
$var wire 1 " no $end
$var reg 4 # i [3:0] $end
$scope module dut $end
$var wire 1 " nq $end
$var wire 1 ! q $end
$var wire 1 $ r $end
$var wire 1 % s $end
$upscope $end
$upscope $end
$enddefinitions $end
$comment Show the parameter values. $end
$dumpall
$end
#0
$dumpvars
0%
0$
b0 #
x"
x!
$end
#5
b1 #
#10
b10 #
#15
b11 #
#20
1!
0"
1%
b100 #
#25
b101 #
#30
b110 #
#35
b111 #
#40
1"
0!
1$
0%
b1000 #
#45
b1001 #
#50
b1010 #
#55
b1011 #
#60
0"
1%
b1100 #
#65
b1101 #
#70
b1110 #
#75
b1111 #
